{
  "sections": {
    "main": {
      "type": "main-page",
      "settings": {
      }
    },
    "16502689640cb70e6f": {
      "type": "html-code",
      "settings": {
        "section_title": "",
        "section_description": "",
        "section_html": "<iframe src=\"https:\/\/www.google.com\/maps\/embed?pb=!1m18!1m12!1m3!1d22920.42878286948!2d-79.13440402543851!3d44.10288603034132!2m3!1f0!2f0!3f0!3m2!1i1024!2i768!4f13.1!3m3!1m2!1s0x89d53be3ca8700f1%3A0x461532be0e1dce3e!2sUxbridge%2C%20ON!5e0!3m2!1sen!2sca!4v1655630406954!5m2!1sen!2sca\" width=\"100%\" height=\"380\" style=\"border:0;\" allowfullscreen=\"\" loading=\"lazy\" referrerpolicy=\"no-referrer-when-downgrade\"><\/iframe>\n\n<h1>Soil Delivery Uxbridge <\/h1>\t\t\t\t\t\n\t\t\t\t\t\n\t\t\t\t\t<p><b>Address:<\/b><br>\n\t\t\t\t\t\tUxbridge, ON<br>\n\t\t\t\t\t\tCanada<br>\n\t\t\t\t\t\tL9L 1W8\n<\/p>\n\t\t\t\t\t<p>\n\t\t\t\t\t\tTelephone: <a class=\"tel\" href=\"tel:416-769-1428\">(416) 769-1428<\/a>\n\t\t\t\t<br>\n\t\t\t\t\t\tFax: <span>(416) 534-4630<\/span>\n<br> Email: <a class=\"mailto\" href=\"mailto:info@purelifebag.com\">info@purelifebag.com<\/a>\t\t\t\t\t<\/p> \n\t\t\t\t\t\n\n\n<style> \n\n  iframe  {  \n    width: 700px; \n    float: left; \n    margin-right: 60px; \n  } \n<\/style>\n<br>\n<br>\n<br>\n\n<h2> Best Sale for Soil Products (2022) - Garden and Grass<\/h2>\nWe are Canada's leading specialist in selling black gold soil, and we promote strong, healthy plants to aid in developing green homes. Our soil is great for interior and exterior use, rich and nutritious, and offers innumerable benefits. In addition, being eco-friendly and biological, it is beneficial to both people and the environment.\n<h2> Benefits of Soil Delivery <\/h2>\n<li>Clean and Precise <a href=\"https:\/\/www.purelifebag.com\/pages\/soil-delivery-Aurora\">Delivery<\/a> <\/li>\n<li>Easy Access <\/li>\n<li>Save Money <\/li>\n<li>Fast Delivery<\/li>\n\n<br>\n<br>\n<br>",
        "section_class": ""
      }
    },
    "16412298855ec48ea3": {
      "type": "image-banner",
      "blocks": {
        "16412298849f537e1d-0": {
          "type": "heading",
          "settings": {
            "heading": "Find The Location Nearest You!",
            "heading_size": "medium"
          }
        },
        "16412298849f537e1d-2": {
          "type": "buttons",
          "settings": {
            "button_label_1": "Delivery Zones",
            "button_label_id": "",
            "button_link_1": "shopify:\/\/pages\/locations",
            "button_style_secondary_1": false,
            "button_label_2": "",
            "button_link_2": "",
            "button_style_secondary_2": false
          }
        }
      },
      "block_order": [
        "16412298849f537e1d-0",
        "16412298849f537e1d-2"
      ],
      "settings": {
        "image": "shopify:\/\/shop_images\/purelifebag-about-us-main-banner_5f2f2c51-b430-4642-9d79-f1030ac1f293.jpg",
        "image_overlay_opacity": 0,
        "image_height": "small",
        "adapt_height_first_image": true,
        "desktop_content_position": "middle-center",
        "show_text_box": false,
        "desktop_content_alignment": "left",
        "color_scheme": "background-1",
        "mobile_content_alignment": "center",
        "stack_images_on_mobile": false,
        "show_text_below": false,
        "custom_class": "spin-wheel main-banner au  text-shad"
      }
    }
  },
  "order": [
    "main",
    "16502689640cb70e6f",
    "16412298855ec48ea3"
  ]
}
